.DS_Store
papexp/__init__.py
papexp/__main__.py
papexp/core.py
papexp/export.py
papexp/nutrition.py
papexp/settings.py
papexp-0.4.1.dist-info/LICENSE
papexp-0.4.1.dist-info/METADATA
papexp-0.4.1.dist-info/WHEEL
papexp-0.4.1.dist-info/top_level.txt
papexp-0.4.1.dist-info/RECORD
