Metadata-Version: 2.1
Name: papexp
Version: 0.4.1
Summary: A simple exporter for the paprika app.
Home-page: UNKNOWN
Author: Chris Nicholson
Author-email: datapolitical@gmail.com
License: UNKNOWN
Platform: UNKNOWN
Classifier: Programming Language :: Python :: 3
Classifier: License :: OSI Approved :: MIT License
Classifier: Operating System :: OS Independent
Requires-Python: >=3.6
License-File: LICENSE
Requires-Dist: requests (>=2.25.0)
Requires-Dist: python-dotenv (>=0.15.0)
Requires-Dist: PyYAML (>=5.4)
